{"title":"ArchLinux+Win10双系统安装过程记录","uid":"43c1e5517339bfb05d371a4410a853ed","slug":"ArchLinux-Win10双系统安装过程记录","date":"2024-11-06T15:26:28.000Z","updated":"2024-11-15T12:55:20.326Z","comments":true,"path":"api/articles/ArchLinux-Win10双系统安装过程记录.json","keywords":null,"cover":"cover/cover3.jpg","content":"<h2 id=\"参考资料\"><a href=\"#参考资料\" class=\"headerlink\" title=\"参考资料\"></a>参考资料</h2><p>参考文章：</p>\n<p><a href=\"https://arch.icekylin.online/guide/rookie/basic-install\">archlinux 基础安装</a></p>\n<p><a href=\"https://www.cnblogs.com/Thato/p/18311683\">ArchLinux Vmware安装指北</a></p>\n<p><a href=\"https://www.cnblogs.com/NexusXian/p/17570030.html\">Archlinux+Windows双系统安装教程(UEFI)2023.7</a></p>\n<p><a href=\"https://zhuanlan.zhihu.com/p/355826301\">VirtualBox 安装 Arch Linux: 从新建虚拟机到图形界面</a></p>\n<p>参考视频</p>\n<p><a href=\"https://www.bilibili.com/video/BV1XY4y1f77S/?spm_id_from=333.337.search-card.all.click&vd_source=0bbd99419aa302dfd5e8f27118f9516d\">【超简单】Windows+Arch Linux双系统双磁盘方案，全程不废话</a></p>\n<p><a href=\"https://www.bilibili.com/video/BV1fk4y1w7wq/?spm_id_from=333.337.search-card.all.click&vd_source=0bbd99419aa302dfd5e8f27118f9516d\">Arch 启动！(Win+ArchLinux双系统安装教程uefi独立home+kde)</a></p>\n<h2 id=\"准备工作\"><a href=\"#准备工作\" class=\"headerlink\" title=\"准备工作\"></a>准备工作</h2><h3 id=\"1、下载-Arch-Linux-镜像\"><a href=\"#1、下载-Arch-Linux-镜像\" class=\"headerlink\" title=\"1、下载 Arch Linux 镜像\"></a>1、下载 Arch Linux 镜像</h3><p>Arch Linux Downloads :<a href=\"https://archlinux.org/download/#http-downloads\">https://archlinux.org/download/#http-downloads</a></p>\n<h3 id=\"2、下载启动盘制作工具\"><a href=\"#2、下载启动盘制作工具\" class=\"headerlink\" title=\"2、下载启动盘制作工具\"></a>2、下载启动盘制作工具</h3><p>Ventory:<a href=\"https://archlinux.org/download/#http-downloads\">https://archlinux.org/download/#http-downloads</a></p>\n<p>Refus:<a href=\"https://rufus.ie/zh/#google_vignette\">https://rufus.ie/zh/#google_vignette</a></p>\n<h3 id=\"3、安装-VirtualBox-选做\"><a href=\"#3、安装-VirtualBox-选做\" class=\"headerlink\" title=\"3、安装 VirtualBox(选做)\"></a>3、安装 VirtualBox(选做)</h3><p>VirtualBox 是由 Oracle 公司开发的免费虚拟机软件。访问以下链接，根据你的宿主（即你所使用的物理意义上的、「真实的」电脑）操作系统下载安装包：</p>\n<p><a href=\"https://www.virtualbox.org/wiki/Downloads\">https://www.virtualbox.org/wiki/Downloads</a></p>\n<h2 id=\"安装\"><a href=\"#安装\" class=\"headerlink\" title=\"安装\"></a>安装</h2>","feature":true,"text":"ArchLinux + Win10 双系统安装过程记录...","permalink":"/post/ArchLinux-Win10双系统安装过程记录","photos":[],"count_time":{"symbolsCount":552,"symbolsTime":"1 mins."},"categories":[{"name":"操作系统","slug":"操作系统","count":2,"path":"api/categories/操作系统.json"}],"tags":[{"name":"操作系统","slug":"操作系统","count":1,"path":"api/tags/操作系统.json"}],"toc":"<ol class=\"toc\"><li class=\"toc-item toc-level-2\"><a class=\"toc-link\" href=\"#%E5%8F%82%E8%80%83%E8%B5%84%E6%96%99\"><span class=\"toc-text\">参考资料</span></a></li><li class=\"toc-item toc-level-2\"><a class=\"toc-link\" href=\"#%E5%87%86%E5%A4%87%E5%B7%A5%E4%BD%9C\"><span class=\"toc-text\">准备工作</span></a><ol class=\"toc-child\"><li class=\"toc-item toc-level-3\"><a class=\"toc-link\" href=\"#1%E3%80%81%E4%B8%8B%E8%BD%BD-Arch-Linux-%E9%95%9C%E5%83%8F\"><span class=\"toc-text\">1、下载 Arch Linux 镜像</span></a></li><li class=\"toc-item toc-level-3\"><a class=\"toc-link\" href=\"#2%E3%80%81%E4%B8%8B%E8%BD%BD%E5%90%AF%E5%8A%A8%E7%9B%98%E5%88%B6%E4%BD%9C%E5%B7%A5%E5%85%B7\"><span class=\"toc-text\">2、下载启动盘制作工具</span></a></li><li class=\"toc-item toc-level-3\"><a class=\"toc-link\" href=\"#3%E3%80%81%E5%AE%89%E8%A3%85-VirtualBox-%E9%80%89%E5%81%9A\"><span class=\"toc-text\">3、安装 VirtualBox(选做)</span></a></li></ol></li><li class=\"toc-item toc-level-2\"><a class=\"toc-link\" href=\"#%E5%AE%89%E8%A3%85\"><span class=\"toc-text\">安装</span></a></li></ol>","author":{"name":"ChenZheng","slug":"blog-author","avatar":"/cover/avatar.jpg","link":"/","description":"幼稚园的小朋友の快乐小屋","socials":{"github":"https://github.com/sjwusj","twitter":"https://github.com/sjwusj","stackoverflow":"","wechat":"","qq":"","weibo":"https://github.com/sjwusj","zhihu":"https://github.com/sjwusj","csdn":"https://github.com/sjwusj","juejin":"j","customs":{}}},"mapped":true,"hidden":false,"prev_post":{"title":"test","uid":"bc567916c4dc0d8169bd26d18e348d36","slug":"test","date":"2024-11-13T10:01:34.000Z","updated":"2024-11-17T07:59:45.953Z","comments":true,"path":"api/articles/test.json","keywords":null,"cover":"cover/JaNing 金克丝4k.jpg","text":"This is an abstract....","permalink":"/post/test","photos":[],"count_time":{"symbolsCount":544,"symbolsTime":"1 mins."},"categories":[],"tags":[],"author":{"name":"ChenZheng","slug":"blog-author","avatar":"/cover/avatar.jpg","link":"/","description":"幼稚园的小朋友の快乐小屋","socials":{"github":"https://github.com/sjwusj","twitter":"https://github.com/sjwusj","stackoverflow":"","wechat":"","qq":"","weibo":"https://github.com/sjwusj","zhihu":"https://github.com/sjwusj","csdn":"https://github.com/sjwusj","juejin":"j","customs":{}}},"feature":true},"next_post":{"title":"Android_End","uid":"c6514010f10f74959b0358300a9b00fc","slug":"Android-End","date":"2024-05-01T05:33:39.000Z","updated":"2024-11-15T12:54:20.593Z","comments":true,"path":"api/articles/Android-End.json","keywords":null,"cover":"cover/cover3.jpg","text":"安卓实训第十二天内容笔记 —— 复习总结...","permalink":"/post/Android-End","photos":[],"count_time":{"symbolsCount":"1.4k","symbolsTime":"1 mins."},"categories":[{"name":"安卓","slug":"安卓","count":10,"path":"api/categories/安卓.json"}],"tags":[{"name":"Android","slug":"Android","count":10,"path":"api/tags/Android.json"}],"author":{"name":"ChenZheng","slug":"blog-author","avatar":"/cover/avatar.jpg","link":"/","description":"幼稚园的小朋友の快乐小屋","socials":{"github":"https://github.com/sjwusj","twitter":"https://github.com/sjwusj","stackoverflow":"","wechat":"","qq":"","weibo":"https://github.com/sjwusj","zhihu":"https://github.com/sjwusj","csdn":"https://github.com/sjwusj","juejin":"j","customs":{}}},"feature":true}}